<?xml version="1.0" standalone="yes"?>
<!-- edited with XMLSPY v5 rel. 4 U (http://www.xmlspy.com) -->
<?Saved @ --2023-05-11T13:52:41-- ?>
<directory>
  <item_list>
    <item>
      <fn>Carissa</fn>
      <ct>18475303582</ct>
      <sd>1</sd>
      <rt>ringerdefault</rt>
      <ad>0</ad>
      <ar>0</ar>
    </item>
    <item>
      <fn>Abigail</fn>
      <ct>16175299958</ct>
      <sd>2</sd>
      <rt>ringerdefault</rt>
      <ad>0</ad>
      <ar>0</ar>
    </item>
    <item>
      <fn>Fisher</fn>
      <ct>7037254042</ct>
      <sd>3</sd>
      <rt>ringerdefault</rt>
      <ad>0</ad>
      <ar>0</ar>
    </item>
    <item>
      <fn>Grace</fn>
      <ct>5083095736</ct>
      <sd>4</sd>
      <rt>ringerdefault</rt>
      <ad>0</ad>
      <ar>0</ar>
    </item>
    <item>
      <fn>Helen</fn>
      <ct>2025503086</ct>
      <sd>5</sd>
      <rt>ringerdefault</rt>
      <ad>0</ad>
      <ar>0</ar>
    </item>
    <item>
      <fn>Amanda</fn>
      <ct>9179169858</ct>
      <sd>6</sd>
      <rt>ringerdefault</rt>
      <ad>0</ad>
      <ar>0</ar>
    </item>
  </item_list>
</directory>
